pycloudstack/__init__.py
pycloudstack/artifacts.py
pycloudstack/cluster.py
pycloudstack/cmdrunner.py
pycloudstack/dut.py
pycloudstack/msr.py
pycloudstack/registry.py
pycloudstack/virtxml.py
pycloudstack/vmguest.py
pycloudstack/vmimg.py
pycloudstack/vmm.py
pycloudstack/vmparam.py
pycloudstack/templates/legacy-base-perf.xml
pycloudstack/templates/legacy-base.xml
pycloudstack/templates/ovmf-base-perf.xml
pycloudstack/templates/ovmf-base.xml
pycloudstack/templates/sgx-base.xml
pycloudstack/templates/tdx-base-perf.xml
pycloudstack/templates/tdx-base.xml
pycloudstack-0.0.10.dist-info/METADATA
pycloudstack-0.0.10.dist-info/WHEEL
pycloudstack-0.0.10.dist-info/top_level.txt
pycloudstack-0.0.10.dist-info/RECORD
